structure_app/__init__.py
structure_app/__main__.py
structure_app/compat.py
structure_app/base/__init__.py
structure_app/base/build_app.py
structure_app/base/pre_build_app.py
structure_app/base/steps.py
structure_app/cli/__init__.py
structure_app/cli/commands.py
structure_app/framework/__init__.py
structure_app/framework/django/README.py
structure_app/framework/django/__init__.py
structure_app/framework/django/env_example.py
structure_app/framework/django/gitignore.py
structure_app/framework/django/wsgi.py
structure_app/framework/django/app/__init__.py
structure_app/framework/django/app/api/__init__.py
structure_app/framework/django/app/api/v1/__init__.py
structure_app/framework/django/app/api/v1/serializers.py
structure_app/framework/django/app/api/v1/urls.py
structure_app/framework/django/app/api/v1/views.py
structure_app/framework/django/app/core/__init__.py
structure_app/framework/django/app/core/handler.py
structure_app/framework/django/app/core/models.py
structure_app/framework/django/app/core/process.py
structure_app/framework/django/app/core/utils.py
structure_app/framework/django/app/core/query_managers/__init__.py
structure_app/framework/django/app/core/query_managers/mixin_queryset.py
structure_app/framework/django/app/core/query_managers/queryset.py
structure_app/framework/django/app/core/utils/__init__.py
structure_app/framework/django/app/core/utils/utils.py
structure_app/framework/django/config/__init__.py
structure_app/framework/django/config/base.py
structure_app/framework/django/config/openapi.py
structure_app/framework/django/config/production.py
structure_app/framework/django/config/staging.py
structure_app/framework/django/requirements/__init__.py
structure_app/framework/django/requirements/requirements.py
structure_app/framework/falcon/README.py
structure_app/framework/falcon/__init__.py
structure_app/framework/falcon/env_example.py
structure_app/framework/falcon/gitignore.py
structure_app/framework/falcon/wsgi.py
structure_app-0.0.57.dist-info/METADATA
structure_app-0.0.57.dist-info/WHEEL
structure_app-0.0.57.dist-info/entry_points.txt
structure_app-0.0.57.dist-info/top_level.txt
structure_app-0.0.57.dist-info/RECORD
