Metadata-Version: 2.1
Name: structure-app
Version: 0.0.57
Summary: create skeleton for framework falcon, fastApi
Home-page: https://gitlab.com/Luisff3rnando/code_generators/-/tree/staging/
Author: Luis Meza
Author-email: luis@luis.com
License: MIT
Platform: Any
Classifier: Development Status :: 3 - Alpha
Classifier: License :: OSI Approved :: MIT License
Classifier: Operating System :: OS Independent
Classifier: Programming Language :: Python
Requires-Python: >=3
Requires-Dist: setuptools
